pons/__init__.py
pons/_abi_types.py
pons/_client.py
pons/_client_rpc.py
pons/_contract.py
pons/_contract_abi.py
pons/_fallback_provider.py
pons/_multicall.py
pons/_provider.py
pons/_signer.py
pons/_utils.py
pons/abi.py
pons/compiler.py
pons/http_provider_server.py
pons/local_provider.py
pons/py.typed
pons-0.10.0.dist-info/WHEEL
pons-0.10.0.dist-info/METADATA
pons-0.10.0.dist-info/licenses/LICENSE.md
pons-0.10.0.dist-info/RECORD
